{
    "symbol": "RIC",
    "name": "AURICOIN",
    "description": "An economic and monetary union of AURICOIN (RIC) is a recurring ambition for humanity from the end of 2010, the creators of AURICOIN carry out studies of an economic policy, a common monetary policy and a common cryptocurrency, AURICOIN (RIC)!",
    "website": "https://auricoin.org/",
    "communities": {
        "email": "admin@auricoin.com",
        "telegram": "https://t.me/auricoin",
        "medium": "https://medium.com/auricoin-es",
        "youtube": "https://www.youtube.com/channel/UC7iekJdPgiC-b6aekMvD8cQ",
        "twitter": "https://twitter.com/AURICOIN_ESP",
        "facebook": "https://www.facebook.com/Auricoin-112391290483987/?modal=admin_todo_tour",
        "github": "https://github.com/AuricoinRic",
        "whitepaper": "https://auricoin.org/assets/docs/whitepaper_es.pdf",
    }
    
}
